mo_testing/__init__.py
mo_testing/fuzzytestcase.py
mo_testing/mocks.py
mo_testing-8.685.25166.dist-info/licenses/LICENSE
mo_testing-8.685.25166.dist-info/METADATA
mo_testing-8.685.25166.dist-info/WHEEL
mo_testing-8.685.25166.dist-info/top_level.txt
mo_testing-8.685.25166.dist-info/RECORD
